odoo/addons/donation_sale/README.rst
odoo/addons/donation_sale/__init__.py
odoo/addons/donation_sale/__manifest__.py
odoo/addons/donation_sale/data/cron.xml
odoo/addons/donation_sale/i18n/de.po
odoo/addons/donation_sale/i18n/donation_sale.pot
odoo/addons/donation_sale/i18n/es.po
odoo/addons/donation_sale/i18n/fr.po
odoo/addons/donation_sale/i18n/it.po
odoo/addons/donation_sale/models/__init__.py
odoo/addons/donation_sale/models/account_move.py
odoo/addons/donation_sale/models/donation_tax_receipt.py
odoo/addons/donation_sale/models/sale.py
odoo/addons/donation_sale/readme/CONTRIBUTORS.rst
odoo/addons/donation_sale/readme/DESCRIPTION.rst
odoo/addons/donation_sale/static/description/icon.png
odoo/addons/donation_sale/static/description/index.html
odoo/addons/donation_sale/tests/__init__.py
odoo/addons/donation_sale/tests/test_donation_sale.py
odoo/addons/donation_sale/views/account_move.xml
odoo/addons/donation_sale/views/donation_tax_receipt.xml
odoo/addons/donation_sale/views/sale_order.xml
odoo14_addon_donation_sale-14.0.1.0.1.dev10.dist-info/METADATA
odoo14_addon_donation_sale-14.0.1.0.1.dev10.dist-info/WHEEL
odoo14_addon_donation_sale-14.0.1.0.1.dev10.dist-info/top_level.txt
odoo14_addon_donation_sale-14.0.1.0.1.dev10.dist-info/RECORD
